surface_distance/__init__.py
surface_distance/lookup_tables.py
surface_distance/metrics.py
CTG_Surface_Distance_Based_Measures-0.1.dist-info/LICENSE
CTG_Surface_Distance_Based_Measures-0.1.dist-info/METADATA
CTG_Surface_Distance_Based_Measures-0.1.dist-info/WHEEL
CTG_Surface_Distance_Based_Measures-0.1.dist-info/top_level.txt
CTG_Surface_Distance_Based_Measures-0.1.dist-info/RECORD
